Metadata-Version: 2.1
Name: test-words-api-client-sdk
Version: 5.0.1
Summary: Words API lets you retrieve information about English words, including definitions, synonyms, rhymes, pronunciation, syllables, and frequency of usage. It also can tell you about relationships between words, for instance that “math” has categories like “algebra” and “geometry”, or that a “finger” is part of a “hand”.
Author-email: Sufyan <muhammad.sufyan@apimatic.io>
Project-URL: Documentation, https://apimatic.io
Keywords: Apimatic
Requires-Python: >=3.7
License-File: LICENSE
Requires-Dist: apimatic-core >=0.2.15,~=0.2.0
Requires-Dist: apimatic-core-interfaces >=0.1.5,~=0.1.0
Requires-Dist: apimatic-requests-client-adapter >=0.1.6,~=0.1.0
Provides-Extra: testutils
Requires-Dist: pytest >=7.2.2 ; extra == 'testutils'
